TextPinner/__init__.py
TextPinner-0.0.7.dist-info/LICENSE
TextPinner-0.0.7.dist-info/METADATA
TextPinner-0.0.7.dist-info/WHEEL
TextPinner-0.0.7.dist-info/top_level.txt
TextPinner-0.0.7.dist-info/RECORD
