Metadata-Version: 2.1
Name: TextPinner
Version: 0.0.7
Summary: A python library for pinning a text to one of texts list. Useful for natural commands parsing.
Home-page: https://github.com/ParisNeo/TextPinner
Author: Saifeddine ALOUI
Author-email: aloui.saifeddine@gmail.com
License: UNKNOWN
Platform: UNKNOWN
Classifier: Programming Language :: Python :: 3.8
Classifier: License :: OSI Approved :: MIT License
Classifier: Operating System :: OS Independent
Requires-Dist: ftfy
Requires-Dist: regex
Requires-Dist: tqdm
Requires-Dist: torch
Requires-Dist: torchvision
Requires-Dist: torchaudio
Requires-Dist: Pillow
Provides-Extra: dev
